tracardi_language_detection/plugin.py
tracardi_language_detection/model/__init__.py
tracardi_language_detection/model/configuration.py
tracardi_language_detection/model/__pycache__/__init__.cpython-38.pyc
tracardi_language_detection/model/__pycache__/configuration.cpython-38.pyc
tracardi_language_detection/service/http_client.py
tracardi_language_detection/service/__pycache__/http_client.cpython-38.pyc
tracardi_language_detection/test/manual_test.py
tracardi_language_detection-0.6.0.dist-info/LICENSE.md
tracardi_language_detection-0.6.0.dist-info/METADATA
tracardi_language_detection-0.6.0.dist-info/WHEEL
tracardi_language_detection-0.6.0.dist-info/top_level.txt
tracardi_language_detection-0.6.0.dist-info/RECORD
