Metadata-Version: 2.1
Name: tracardi-language-detection
Version: 0.6.0
Summary: This plugin detect language from given string with meaningcloud API
Home-page: UNKNOWN
Author: Patryk Migaj
Author-email: patromi123@gmail.com
License: UNKNOWN
Keywords: tracardi,plugin
Platform: UNKNOWN
Classifier: Programming Language :: Python :: 3
Classifier: License :: OSI Approved :: MIT License
Classifier: Operating System :: OS Independent
Requires-Python: >=3.8
License-File: LICENSE.md
Requires-Dist: tracardi-plugin-sdk (>=0.6.22)
Requires-Dist: tracardi (<0.7.0,>=0.6.18)
